LICENSE.txt
MANIFEST.in
README.md
files.txt
setup.cfg
setup.py
moRFeusQt/__init__.py
moRFeusQt/__main__.py
moRFeusQt/mrf.py
moRFeusQt/mrfmorse.py
moRFeusQt/mrfmulti.py
moRFeusQt/mrfplot.py
moRFeusQt/mrfqt.py
moRFeusQt/mrfsoapy.py
moRFeusQt/mrftcp.py
moRFeusQt/mrfui.py
moRFeusQt.egg-info/PKG-INFO
moRFeusQt.egg-info/SOURCES.txt
moRFeusQt.egg-info/dependency_links.txt
moRFeusQt.egg-info/entry_points.txt
moRFeusQt.egg-info/requires.txt
moRFeusQt.egg-info/top_level.txt
tests/__init__.py
tests/test_mrf.py