Metadata-Version: 2.1
Name: moRFeusQt
Version: 3.333
Summary: UNKNOWN
Home-page: https://github.com/Psynosaur/moRFeus_Qt
Author: Ohan Smit
Author-email: psynosaur@gmail.com
License: LICENSE.txt
Platform: UNKNOWN
